{
  "slug": "calendar-calculator",
  "title": "calendar calculator — Add/Subtract Dates, Day Counter, Business Days",
  "canonical": "https://calcdomain.com/calendar-calculator",
  "version": "0.1.0-draft",
  "lastCodeUpdateISO": "2026-01-19",
  "verifiedByName": "Ugo Candido",
  "verifiedProfileUrl": "https://calcdomain.com/ugocandido",
  "verifiedLinkedInUrl": "https://www.linkedin.com/in/ugocandido92821/",
  "formulas": [
    {
      "title": "Formula (extracted LaTeX)",
      "latex": "\\Delta d = \\mathrm{days}(d_2) - \\mathrm{days}(d_1)",
      "raw": "\\Delta d = \\mathrm{days}(d_2) - \\mathrm{days}(d_1)"
    },
    {
      "title": "Formula (extracted LaTeX)",
      "latex": "\\Delta y = y_2 - y_1,\\quad \\Delta m = m_2 - m_1,\\quad \\Delta d' = d_2 - d_1",
      "raw": "\\Delta y = y_2 - y_1,\\quad \\Delta m = m_2 - m_1,\\quad \\Delta d' = d_2 - d_1"
    },
    {
      "title": "Formula (extracted LaTeX)",
      "latex": "\\mathrm{add}(y,m,d; \\Delta y,\\Delta m,\\Delta d) = \\mathrm{clampEOM}\\bigl(y+\\Delta y,\\; m+\\Delta m,\\; d\\bigr) + \\Delta d",
      "raw": "\\mathrm{add}(y,m,d; \\Delta y,\\Delta m,\\Delta d) = \\mathrm{clampEOM}\\bigl(y+\\Delta y,\\; m+\\Delta m,\\; d\\bigr) + \\Delta d"
    },
    {
      "title": "Formula (extracted LaTeX)",
      "latex": "\\mathrm{bizdays}(d_1,d_2,H)=\\sum_{t=d_1}^{d_2-1}\\mathbf{1}\\bigl(\\mathrm{weekday}(t)\\in\\{1,\\dots,5\\}\\land t\\notin H\\bigr)",
      "raw": "\\mathrm{bizdays}(d_1,d_2,H)=\\sum_{t=d_1}^{d_2-1}\\mathbf{1}\\bigl(\\mathrm{weekday}(t)\\in\\{1,\\dots,5\\}\\land t\\notin H\\bigr)"
    },
    {
      "title": "Formula (extracted LaTeX)",
      "latex": "\\mathrm{week}(d)=\\mathrm{ISOWeekNumber}(d),\\quad \\mathrm{weekday}_{\\mathrm{ISO}}\\in\\{1\\ldots7\\}",
      "raw": "\\mathrm{week}(d)=\\mathrm{ISOWeekNumber}(d),\\quad \\mathrm{weekday}_{\\mathrm{ISO}}\\in\\{1\\ldots7\\}"
    },
    {
      "title": "Formula (extracted text)",
      "latex": "",
      "raw": "Date difference (days): \\[ \\Delta d = \\mathrm{days}(d_2) - \\mathrm{days}(d_1) \\] Y–M–D breakdown (proleptic Gregorian): \\[ \\Delta y = y_2 - y_1,\\quad \\Delta m = m_2 - m_1,\\quad \\Delta d' = d_2 - d_1 \\] Adjust \\(\\Delta m,\\Delta d'\\) by borrowing/carrying based on month lengths and leap-year rules. Add/Subtract with end-of-month safety: \\[ \\mathrm{add}(y,m,d; \\Delta y,\\Delta m,\\Delta d) = \\mathrm{clampEOM}\\bigl(y+\\Delta y,\\; m+\\Delta m,\\; d\\bigr) + \\Delta d \\] where \\(\\mathrm{clampEOM}\\) sets the day to the month's last valid day if needed. Business days, excluding weekends & holidays: \\[ \\mathrm{bizdays}(d_1,d_2,H)=\\sum_{t=d_1}^{d_2-1}\\mathbf{1}\\bigl(\\mathrm{weekday}(t)\\in\\{1,\\dots,5\\}\\land t\\notin H\\bigr) \\] ISO week number (ISO 8601): \\[ \\mathrm{week}(d)=\\mathrm{ISOWeekNumber}(d),\\quad \\mathrm{weekday}_{\\mathrm{ISO}}\\in\\{1\\ldots7\\} \\]"
    }
  ],
  "variables": [],
  "sources": [
    {
      "label": "ISO overview",
      "publisher": "iso.org",
      "url": "https://www.iso.org/iso-8601-date-and-time-format.html",
      "accessedISO": "2026-01-19"
    },
    {
      "label": "Home",
      "publisher": "calcdomain.com",
      "url": "https://calcdomain.com/",
      "accessedISO": "2026-01-19"
    },
    {
      "label": "Everyday Life",
      "publisher": "calcdomain.com",
      "url": "https://calcdomain.com/lifestyle-everyday",
      "accessedISO": "2026-01-19"
    },
    {
      "label": "Time and Date",
      "publisher": "calcdomain.com",
      "url": "https://calcdomain.com/subcategories/time-date",
      "accessedISO": "2026-01-19"
    },
    {
      "label": "ISO week date summary",
      "publisher": "en.wikipedia.org",
      "url": "https://en.wikipedia.org/wiki/ISO_week_date",
      "accessedISO": "2026-01-19"
    }
  ],
  "changelog": [
    {
      "dateISO": "2026-01-19",
      "version": "0.1.0-draft",
      "changes": [
        "Initial audit spec draft generated from HTML extraction (review required).",
        "Verify formulas match the calculator engine and convert any text-only formulas to LaTeX.",
        "Confirm sources are authoritative and relevant to the calculator methodology."
      ]
    }
  ]
}
