{
  "slug": "cooking-calculator",
  "title": "Cooking Calculator — Scale Recipes, Convert Units, Estimate Roast Times",
  "canonical": "https://calcdomain.com/cooking-calculator",
  "version": "0.1.0-draft",
  "lastCodeUpdateISO": "2026-01-19",
  "verifiedByName": "Ugo Candido",
  "verifiedProfileUrl": "https://calcdomain.com/ugocandido",
  "verifiedLinkedInUrl": "https://www.linkedin.com/in/ugocandido92821/",
  "formulas": [
    {
      "title": "Formula (extracted LaTeX)",
      "latex": "q_{new} = q_{orig} \\times \\frac{S_{new}}{S_{orig}}",
      "raw": "q_{new} = q_{orig} \\times \\frac{S_{new}}{S_{orig}}"
    },
    {
      "title": "Formula (extracted LaTeX)",
      "latex": "m = \\rho \\cdot V \\quad\\text{and}\\quad V = \\frac{m}{\\rho}",
      "raw": "m = \\rho \\cdot V \\quad\\text{and}\\quad V = \\frac{m}{\\rho}"
    },
    {
      "title": "Formula (extracted LaTeX)",
      "latex": "t = a \\cdot w + b",
      "raw": "t = a \\cdot w + b"
    },
    {
      "title": "Formula (extracted text)",
      "latex": "",
      "raw": "Recipe scaling: $$q_{new} = q_{orig} \\times \\frac{S_{new}}{S_{orig}}$$ Mass–volume conversion with density: $$m = \\rho \\cdot V \\quad\\text{and}\\quad V = \\frac{m}{\\rho}$$ where \\( \\rho \\) is ingredient-specific (e.g., g/mL). Roast time (affine model): $$t = a \\cdot w + b$$ where \\(t\\) is time, \\(w\\) is weight, \\(a,b\\) depend on meat type and oven. Convection typically reduces \\(t\\) by ~15–20%."
    }
  ],
  "variables": [],
  "sources": [
    {
      "label": "Home",
      "publisher": "calcdomain.com",
      "url": "https://calcdomain.com/",
      "accessedISO": "2026-01-19"
    },
    {
      "label": "Lifestyle Everyday",
      "publisher": "calcdomain.com",
      "url": "https://calcdomain.com/lifestyle-everyday",
      "accessedISO": "2026-01-19"
    },
    {
      "label": "Hobbies",
      "publisher": "calcdomain.com",
      "url": "https://calcdomain.com/subcategories/hobbies",
      "accessedISO": "2026-01-19"
    },
    {
      "label": "King Arthur Baking – Ingredient Weight Chart",
      "publisher": "kingarthurbaking.com",
      "url": "https://www.kingarthurbaking.com/learn/ingredient-weight-chart",
      "accessedISO": "2026-01-19"
    }
  ],
  "changelog": [
    {
      "dateISO": "2026-01-19",
      "version": "0.1.0-draft",
      "changes": [
        "Initial audit spec draft generated from HTML extraction (review required).",
        "Verify formulas match the calculator engine and convert any text-only formulas to LaTeX.",
        "Confirm sources are authoritative and relevant to the calculator methodology."
      ]
    }
  ]
}
