{
  "slug": "dodecagon-calculator",
  "title": "Decagon Calculator (Area, Perimeter, Side, Inradius, Circumradius)",
  "canonical": "https://calcdomain.com/decagon-calculator",
  "version": "0.1.0-draft",
  "lastCodeUpdateISO": "2026-01-19",
  "verifiedByName": "Ugo Candido",
  "verifiedProfileUrl": "https://calcdomain.com/ugocandido",
  "verifiedLinkedInUrl": "https://www.linkedin.com/in/ugocandido92821/",
  "formulas": [
    {
      "title": "Formula (extracted LaTeX)",
      "latex": "','\\",
      "raw": "','\\"
    },
    {
      "title": "Formula (extracted text)",
      "latex": "",
      "raw": "Perimeter: \\( P = 10s \\) Area: \\( A = \\frac{5}{2} s^2 \\sqrt{5 + 2\\sqrt{5}} \\approx 7.69420884\\, s^2 \\) Inradius (apothem): \\( r = \\dfrac{s}{2 \\tan(\\pi/10)} \\) Circumradius: \\( R = \\dfrac{s}{2 \\sin(\\pi/10)} \\approx 1.618\\, s \\)"
    }
  ],
  "variables": [],
  "sources": [],
  "changelog": [
    {
      "dateISO": "2026-01-19",
      "version": "0.1.0-draft",
      "changes": [
        "Initial audit spec draft generated from HTML extraction (review required).",
        "Verify formulas match the calculator engine and convert any text-only formulas to LaTeX.",
        "Confirm sources are authoritative and relevant to the calculator methodology."
      ]
    }
  ]
}
