{
  "slug": "drag-coefficient",
  "title": "Drag Coefficient Calculator",
  "canonical": "https://calcdomain.com/drag-coefficient",
  "version": "0.1.0-draft",
  "lastCodeUpdateISO": "2026-01-19",
  "verifiedByName": "Ugo Candido",
  "verifiedProfileUrl": "https://calcdomain.com/ugocandido",
  "verifiedLinkedInUrl": "https://www.linkedin.com/in/ugocandido92821/",
  "formulas": [
    {
      "title": "Formula (extracted LaTeX)",
      "latex": "','",
      "raw": "','"
    },
    {
      "title": "Formula (extracted text)",
      "latex": "",
      "raw": "The drag coefficient (Cd) is calculated using the formula: \\( C_d = \\frac{2F_d}{\\rho v^2 A} \\) where: Fd is the drag force in Newtons \\(\\rho\\) is the fluid density in kg/m3 v is the velocity in m/s A is the frontal area in m2"
    }
  ],
  "variables": [],
  "sources": [
    {
      "label": "Learn more from NASA",
      "publisher": "nasa.gov",
      "url": "https://www.nasa.gov/aero",
      "accessedISO": "2026-01-19"
    }
  ],
  "changelog": [
    {
      "dateISO": "2026-01-19",
      "version": "0.1.0-draft",
      "changes": [
        "Initial audit spec draft generated from HTML extraction (review required).",
        "Verify formulas match the calculator engine and convert any text-only formulas to LaTeX.",
        "Confirm sources are authoritative and relevant to the calculator methodology."
      ]
    }
  ]
}
