{
  "slug": "flooring-calculator",
  "title": "Project Layout & Design – Flooring Calculator",
  "canonical": "https://calcdomain.com/flooring-calculator",
  "version": "0.1.0-draft",
  "lastCodeUpdateISO": "2026-01-19",
  "verifiedByName": "Ugo Candido",
  "verifiedProfileUrl": "https://calcdomain.com/ugocandido",
  "verifiedLinkedInUrl": "https://www.linkedin.com/in/ugocandido92821/",
  "formulas": [
    {
      "title": "Formula (extracted LaTeX)",
      "latex": "\\text{Area}_{\\text{room}} = L \\times W",
      "raw": "\\text{Area}_{\\text{room}} = L \\times W"
    },
    {
      "title": "Formula (extracted LaTeX)",
      "latex": "\\text{Module}_{\\text{eff}}^x = \\text{module}_x + g, \\quad \\text{Module}_{\\text{eff}}^y = \\text{module}_y + g",
      "raw": "\\text{Module}_{\\text{eff}}^x = \\text{module}_x + g, \\quad \\text{Module}_{\\text{eff}}^y = \\text{module}_y + g"
    },
    {
      "title": "Formula (extracted LaTeX)",
      "latex": "\\text{Units}_{\\text{net}} = \\frac{\\sum (L_i \\cdot W_i)}{\\text{Module}_{\\text{eff}}^x \\cdot \\text{Module}_{\\text{eff}}^y}",
      "raw": "\\text{Units}_{\\text{net}} = \\frac{\\sum (L_i \\cdot W_i)}{\\text{Module}_{\\text{eff}}^x \\cdot \\text{Module}_{\\text{eff}}^y}"
    },
    {
      "title": "Formula (extracted LaTeX)",
      "latex": "\\text{Units}_{\\text{final}} = \\left\\lceil \\text{Units}_{\\text{net}} \\cdot (1 + w) \\cdot p_f \\right\\rceil",
      "raw": "\\text{Units}_{\\text{final}} = \\left\\lceil \\text{Units}_{\\text{net}} \\cdot (1 + w) \\cdot p_f \\right\\rceil"
    },
    {
      "title": "Formula (extracted text)",
      "latex": "",
      "raw": "\\[\\text{Area}_{\\text{room}} = L \\times W\\] \\[\\text{Module}_{\\text{eff}}^x = \\text{module}_x + g, \\quad \\text{Module}_{\\text{eff}}^y = \\text{module}_y + g\\] \\[\\text{Units}_{\\text{net}} = \\frac{\\sum (L_i \\cdot W_i)}{\\text{Module}_{\\text{eff}}^x \\cdot \\text{Module}_{\\text{eff}}^y}\\] \\[\\text{Units}_{\\text{final}} = \\left\\lceil \\text{Units}_{\\text{net}} \\cdot (1 + w) \\cdot p_f \\right\\rceil\\] where \\\\ \\(g\\) = grout/joint width (converted to same units as module), \\(w\\) = waste fraction (e.g., 0.10), and \\(p_f\\) = pattern factor."
    }
  ],
  "variables": [],
  "sources": [
    {
      "label": "Home",
      "publisher": "calcdomain.com",
      "url": "https://calcdomain.com/",
      "accessedISO": "2026-01-19"
    },
    {
      "label": "Construction",
      "publisher": "calcdomain.com",
      "url": "https://calcdomain.com/construction-diy",
      "accessedISO": "2026-01-19"
    },
    {
      "label": "TCNA Handbook for Ceramic, Glass, and Stone Tile Installation (latest edition)",
      "publisher": "tcnatile.com",
      "url": "https://www.tcnatile.com/technical-services/faq/68-what-is-the-tcna-handbook.html",
      "accessedISO": "2026-01-19"
    },
    {
      "label": "ANSI A108/A118/A136.1",
      "publisher": "ansi.org",
      "url": "https://www.ansi.org/",
      "accessedISO": "2026-01-19"
    },
    {
      "label": "NWFA Wood Flooring Installation Guidelines",
      "publisher": "nwfa.org",
      "url": "https://nwfa.org/technical-standards/",
      "accessedISO": "2026-01-19"
    },
    {
      "label": "Concrete Slab Calculator",
      "publisher": "calcdomain.com",
      "url": "https://calcdomain.com/concrete-slab-calculator",
      "accessedISO": "2026-01-19"
    },
    {
      "label": "Paint Coverage Calculator",
      "publisher": "calcdomain.com",
      "url": "https://calcdomain.com/paint-calculator",
      "accessedISO": "2026-01-19"
    }
  ],
  "changelog": [
    {
      "dateISO": "2026-01-19",
      "version": "0.1.0-draft",
      "changes": [
        "Initial audit spec draft generated from HTML extraction (review required).",
        "Verify formulas match the calculator engine and convert any text-only formulas to LaTeX.",
        "Confirm sources are authoritative and relevant to the calculator methodology."
      ]
    }
  ]
}
