{
  "slug": "force",
  "title": "Force Calculator | Science › Physics",
  "canonical": "https://calcdomain.com/force",
  "version": "0.1.0-draft",
  "lastCodeUpdateISO": "2026-01-19",
  "verifiedByName": "Ugo Candido",
  "verifiedProfileUrl": "https://calcdomain.com/ugocandido",
  "verifiedLinkedInUrl": "https://www.linkedin.com/in/ugocandido92821/",
  "formulas": [
    {
      "title": "Formula (extracted LaTeX)",
      "latex": "F = m \\cdot a",
      "raw": "F = m \\cdot a"
    },
    {
      "title": "Formula (extracted LaTeX)",
      "latex": "W = m \\cdot g",
      "raw": "W = m \\cdot g"
    },
    {
      "title": "Formula (extracted LaTeX)",
      "latex": "1~\\mathrm{N} = 1~\\mathrm{kg}\\cdot\\mathrm{m/s^2}, \\quad 1~\\mathrm{lbf} = 4.4482216152605~\\mathrm{N}",
      "raw": "1~\\mathrm{N} = 1~\\mathrm{kg}\\cdot\\mathrm{m/s^2}, \\quad 1~\\mathrm{lbf} = 4.4482216152605~\\mathrm{N}"
    },
    {
      "title": "Formula (extracted LaTeX)",
      "latex": "F = m \\cdot a = 75~\\mathrm{kg} \\times 2.5~\\mathrm{m/s^2} = 187.5~\\mathrm{N}",
      "raw": "F = m \\cdot a = 75~\\mathrm{kg} \\times 2.5~\\mathrm{m/s^2} = 187.5~\\mathrm{N}"
    },
    {
      "title": "Formula (extracted LaTeX)",
      "latex": "kN = \\frac{187.5}{1000} = 0.1875~\\mathrm{kN}, \\quad lbf = \\frac{187.5}{4.4482216152605} \\approx 42.15~\\mathrm{lbf}",
      "raw": "kN = \\frac{187.5}{1000} = 0.1875~\\mathrm{kN}, \\quad lbf = \\frac{187.5}{4.4482216152605} \\approx 42.15~\\mathrm{lbf}"
    },
    {
      "title": "Formula (extracted text)",
      "latex": "",
      "raw": "Newton’s Second Law: $$F = m \\cdot a$$ Weight (force due to gravity): $$W = m \\cdot g$$ Unit relations: $$1~\\mathrm{N} = 1~\\mathrm{kg}\\cdot\\mathrm{m/s^2}, \\quad 1~\\mathrm{lbf} = 4.4482216152605~\\mathrm{N}$$"
    },
    {
      "title": "Formula (extracted text)",
      "latex": "",
      "raw": "$$F = m \\cdot a = 75~\\mathrm{kg} \\times 2.5~\\mathrm{m/s^2} = 187.5~\\mathrm{N}$$ Convert to other units: $$kN = \\frac{187.5}{1000} = 0.1875~\\mathrm{kN}, \\quad lbf = \\frac{187.5}{4.4482216152605} \\approx 42.15~\\mathrm{lbf}$$"
    }
  ],
  "variables": [],
  "sources": [
    {
      "label": "NASA Planetary Fact Sheets",
      "publisher": "nssdc.gsfc.nasa.gov",
      "url": "https://nssdc.gsfc.nasa.gov/planetary/factsheet/",
      "accessedISO": "2026-01-19"
    },
    {
      "label": "Science",
      "publisher": "calcdomain.com",
      "url": "https://calcdomain.com/science",
      "accessedISO": "2026-01-19"
    },
    {
      "label": "Physics",
      "publisher": "calcdomain.com",
      "url": "https://calcdomain.com/subcategories/physics",
      "accessedISO": "2026-01-19"
    },
    {
      "label": "SI Brochure",
      "publisher": "bipm.org",
      "url": "https://www.bipm.org/en/publications/si-brochure",
      "accessedISO": "2026-01-19"
    }
  ],
  "changelog": [
    {
      "dateISO": "2026-01-19",
      "version": "0.1.0-draft",
      "changes": [
        "Initial audit spec draft generated from HTML extraction (review required).",
        "Verify formulas match the calculator engine and convert any text-only formulas to LaTeX.",
        "Confirm sources are authoritative and relevant to the calculator methodology."
      ]
    }
  ]
}
