{
  "slug": "knitting-gauge",
  "title": "Knitting Gauge Calculator",
  "canonical": "https://calcdomain.com/knitting-gauge",
  "version": "0.1.0-draft",
  "lastCodeUpdateISO": "2026-01-19",
  "verifiedByName": "Ugo Candido",
  "verifiedProfileUrl": "https://calcdomain.com/ugocandido",
  "verifiedLinkedInUrl": "https://www.linkedin.com/in/ugocandido92821/",
  "formulas": [
    {
      "title": "Formula (extracted LaTeX)",
      "latex": "','",
      "raw": "','"
    },
    {
      "title": "Formula (extracted text)",
      "latex": "",
      "raw": "Stitches per Inch = Number of Stitches / Length of Swatch Rows per Inch = Number of Rows / Length of Swatch"
    }
  ],
  "variables": [],
  "sources": [
    {
      "label": "Home",
      "publisher": "calcdomain.com",
      "url": "https://calcdomain.com/",
      "accessedISO": "2026-01-19"
    },
    {
      "label": "Lifestyle & Everyday",
      "publisher": "calcdomain.com",
      "url": "https://calcdomain.com/lifestyle-everyday",
      "accessedISO": "2026-01-19"
    },
    {
      "label": "Hobbies",
      "publisher": "calcdomain.com",
      "url": "https://calcdomain.com/subcategories/hobbies",
      "accessedISO": "2026-01-19"
    },
    {
      "label": "Learn more about knitting math.",
      "publisher": "knitterskitchen.com",
      "url": "https://knitterskitchen.com/2018/01/31/knitting-math-re-calculating-your-size/",
      "accessedISO": "2026-01-19"
    },
    {
      "label": "Candle Wax Calculator",
      "publisher": "calcdomain.com",
      "url": "https://calcdomain.com/candle-making",
      "accessedISO": "2026-01-19"
    },
    {
      "label": "Sewing Yardage Calculator",
      "publisher": "calcdomain.com",
      "url": "https://calcdomain.com/sewing-yardage",
      "accessedISO": "2026-01-19"
    },
    {
      "label": "Poker Odds Calculator",
      "publisher": "calcdomain.com",
      "url": "https://calcdomain.com/poker-odds",
      "accessedISO": "2026-01-19"
    },
    {
      "label": "Darts Checkout Calculator",
      "publisher": "calcdomain.com",
      "url": "https://calcdomain.com/darts-checkout",
      "accessedISO": "2026-01-19"
    }
  ],
  "changelog": [
    {
      "dateISO": "2026-01-19",
      "version": "0.1.0-draft",
      "changes": [
        "Initial audit spec draft generated from HTML extraction (review required).",
        "Verify formulas match the calculator engine and convert any text-only formulas to LaTeX.",
        "Confirm sources are authoritative and relevant to the calculator methodology."
      ]
    }
  ]
}
