{
  "slug": "mph-to-feet-per-second",
  "title": "MPH to Feet per Second Converter | Miles per Hour to ft/s",
  "canonical": "https://calcdomain.com/mph-to-feet-per-second",
  "version": "0.1.0-draft",
  "lastCodeUpdateISO": "2026-01-19",
  "verifiedByName": "Ugo Candido",
  "verifiedProfileUrl": "https://calcdomain.com/ugocandido",
  "verifiedLinkedInUrl": "https://www.linkedin.com/in/ugocandido92821/",
  "formulas": [
    {
      "title": "Formula (extracted LaTeX)",
      "latex": "','\\",
      "raw": "','\\"
    },
    {
      "title": "Formula (extracted text)",
      "latex": "",
      "raw": "1 mile = 5280 feet 1 hour = 3600 seconds 1 mph = 5280 รท 3600 = 1.466666... ft/s"
    },
    {
      "title": "Formula (extracted text)",
      "latex": "",
      "raw": "ft/s = mph ร 1.46667"
    }
  ],
  "variables": [],
  "sources": [],
  "changelog": [
    {
      "dateISO": "2026-01-19",
      "version": "0.1.0-draft",
      "changes": [
        "Initial audit spec draft generated from HTML extraction (review required).",
        "Verify formulas match the calculator engine and convert any text-only formulas to LaTeX.",
        "Confirm sources are authoritative and relevant to the calculator methodology."
      ]
    }
  ]
}
