{
  "slug": "power",
  "title": "Power Calculator | Science • Physics",
  "canonical": "https://calcdomain.com/power",
  "version": "0.1.0-draft",
  "lastCodeUpdateISO": "2026-01-19",
  "verifiedByName": "Ugo Candido",
  "verifiedProfileUrl": "https://calcdomain.com/ugocandido",
  "verifiedLinkedInUrl": "https://www.linkedin.com/in/ugocandido92821/",
  "formulas": [
    {
      "title": "Formula (extracted LaTeX)",
      "latex": "','",
      "raw": "','"
    },
    {
      "title": "Formula (extracted LaTeX)",
      "latex": "P = V \\cdot I",
      "raw": "P = V \\cdot I"
    },
    {
      "title": "Formula (extracted LaTeX)",
      "latex": "P = I^2 R = \\frac{V^2}{R}",
      "raw": "P = I^2 R = \\frac{V^2}{R}"
    },
    {
      "title": "Formula (extracted LaTeX)",
      "latex": "P = V_{\\mathrm{rms}} \\cdot I_{\\mathrm{rms}} \\cdot \\cos\\varphi",
      "raw": "P = V_{\\mathrm{rms}} \\cdot I_{\\mathrm{rms}} \\cdot \\cos\\varphi"
    },
    {
      "title": "Formula (extracted LaTeX)",
      "latex": "P = \\sqrt{3}\\; V_{LL} \\cdot I_{L} \\cdot \\cos\\varphi",
      "raw": "P = \\sqrt{3}\\; V_{LL} \\cdot I_{L} \\cdot \\cos\\varphi"
    },
    {
      "title": "Formula (extracted LaTeX)",
      "latex": "S = V_{\\mathrm{rms}} \\cdot I_{\\mathrm{rms}}",
      "raw": "S = V_{\\mathrm{rms}} \\cdot I_{\\mathrm{rms}}"
    },
    {
      "title": "Formula (extracted text)",
      "latex": "",
      "raw": "DC: $$P = V \\cdot I$$ Resistive identity: $$P = I^2 R = \\frac{V^2}{R}$$ Single-phase AC (real power): $$P = V_{\\mathrm{rms}} \\cdot I_{\\mathrm{rms}} \\cdot \\cos\\varphi$$ Three-phase AC (real power, 3-wire balanced): $$P = \\sqrt{3}\\; V_{LL} \\cdot I_{L} \\cdot \\cos\\varphi$$ Single-phase apparent power: $$S = V_{\\mathrm{rms}} \\cdot I_{\\mathrm{rms}}$$ Three-phase apparent power: $$S = \\sqrt{3}\\; V_{LL} \\cdot I_{L}$$"
    }
  ],
  "variables": [],
  "sources": [
    {
      "label": "Science",
      "publisher": "calcdomain.com",
      "url": "https://calcdomain.com/science",
      "accessedISO": "2026-01-19"
    },
    {
      "label": "Physics",
      "publisher": "calcdomain.com",
      "url": "https://calcdomain.com/subcategories/physics",
      "accessedISO": "2026-01-19"
    },
    {
      "label": "View the standard",
      "publisher": "standards.ieee.org",
      "url": "https://standards.ieee.org/standard/1459-2010.html",
      "accessedISO": "2026-01-19"
    }
  ],
  "changelog": [
    {
      "dateISO": "2026-01-19",
      "version": "0.1.0-draft",
      "changes": [
        "Initial audit spec draft generated from HTML extraction (review required).",
        "Verify formulas match the calculator engine and convert any text-only formulas to LaTeX.",
        "Confirm sources are authoritative and relevant to the calculator methodology."
      ]
    }
  ]
}
