{
  "slug": "relative-risk",
  "title": "Relative Risk (Risk Ratio) Calculator",
  "canonical": "https://calcdomain.com/relative-risk",
  "version": "0.1.0-draft",
  "lastCodeUpdateISO": "2026-01-19",
  "verifiedByName": "Ugo Candido",
  "verifiedProfileUrl": "https://calcdomain.com/ugocandido",
  "verifiedLinkedInUrl": "https://www.linkedin.com/in/ugocandido92821/",
  "formulas": [
    {
      "title": "Formula (extracted LaTeX)",
      "latex": "','",
      "raw": "','"
    },
    {
      "title": "Formula (extracted text)",
      "latex": "",
      "raw": "Relative Risk (RR) is calculated as: RR = (a / (a + b)) / (c / (c + d)) where: a = Exposed Group with Outcome b = Exposed Group without Outcome c = Control Group with Outcome d = Control Group without Outcome"
    }
  ],
  "variables": [],
  "sources": [
    {
      "label": "MedCalc",
      "publisher": "medcalc.org",
      "url": "https://www.medcalc.org/en/manual/relativerisk.php",
      "accessedISO": "2026-01-19"
    }
  ],
  "changelog": [
    {
      "dateISO": "2026-01-19",
      "version": "0.1.0-draft",
      "changes": [
        "Initial audit spec draft generated from HTML extraction (review required).",
        "Verify formulas match the calculator engine and convert any text-only formulas to LaTeX.",
        "Confirm sources are authoritative and relevant to the calculator methodology."
      ]
    }
  ]
}
