{
  "slug": "semaphore-translator",
  "title": "Semaphore Flag Translator | Flag Positions Explained",
  "canonical": "https://calcdomain.com/semaphore-translator",
  "version": "0.1.0-draft",
  "lastCodeUpdateISO": "2026-01-19",
  "verifiedByName": "Ugo Candido",
  "verifiedProfileUrl": "https://calcdomain.com/ugocandido",
  "verifiedLinkedInUrl": "https://www.linkedin.com/in/ugocandido92821/",
  "formulas": [],
  "variables": [],
  "sources": [
    {
      "label": "Home",
      "publisher": "calcdomain.com",
      "url": "https://calcdomain.com/",
      "accessedISO": "2026-01-19"
    },
    {
      "label": "Lifestyle & Everyday",
      "publisher": "calcdomain.com",
      "url": "https://calcdomain.com/lifestyle-everyday",
      "accessedISO": "2026-01-19"
    },
    {
      "label": "Miscellaneous",
      "publisher": "calcdomain.com",
      "url": "https://calcdomain.com/subcategories/miscellaneous",
      "accessedISO": "2026-01-19"
    },
    {
      "label": "International Maritime Organization — ICS",
      "publisher": "imo.org",
      "url": "https://www.imo.org/en/OurWork/Safety/Pages/International-Code-of-Signals.aspx",
      "accessedISO": "2026-01-19"
    },
    {
      "label": "USCG Navigation Center: Semaphore basics",
      "publisher": "navcen.uscg.gov",
      "url": "https://www.navcen.uscg.gov/?pageName=mtSemFlag",
      "accessedISO": "2026-01-19"
    },
    {
      "label": "NATO Phonetic Alphabet",
      "publisher": "calcdomain.com",
      "url": "https://calcdomain.com/phonetic-alphabet-translator",
      "accessedISO": "2026-01-19"
    },
    {
      "label": "Morse Code Translator",
      "publisher": "calcdomain.com",
      "url": "https://calcdomain.com/morse-code-translator",
      "accessedISO": "2026-01-19"
    },
    {
      "label": "Braille Translator",
      "publisher": "calcdomain.com",
      "url": "https://calcdomain.com/braille-translator",
      "accessedISO": "2026-01-19"
    }
  ],
  "changelog": [
    {
      "dateISO": "2026-01-19",
      "version": "0.1.0-draft",
      "changes": [
        "Initial audit spec draft generated from HTML extraction (review required).",
        "Verify formulas match the calculator engine and convert any text-only formulas to LaTeX.",
        "Confirm sources are authoritative and relevant to the calculator methodology."
      ]
    }
  ]
}
