{
  "slug": "subnet-calculator",
  "title": "Subnet Calculator — IPv4 CIDR, Mask, Hosts, Ranges",
  "canonical": "https://calcdomain.com/subnet-calculator",
  "version": "0.1.0-draft",
  "lastCodeUpdateISO": "2026-01-19",
  "verifiedByName": "Ugo Candido",
  "verifiedProfileUrl": "https://calcdomain.com/ugocandido",
  "verifiedLinkedInUrl": "https://www.linkedin.com/in/ugocandido92821/",
  "formulas": [
    {
      "title": "Formula (extracted LaTeX)",
      "latex": "\\text{Total addresses} = 2^{32-p}",
      "raw": "\\text{Total addresses} = 2^{32-p}"
    },
    {
      "title": "Formula (extracted LaTeX)",
      "latex": "\\text{Usable hosts} = \\begin{cases} 2^{32-p} - 2, & \\text{if } p \\le 30 \\\\ 2, & \\text{if } p = 31 \\text{ (RFC 3021 point-to-point)} \\\\ 1, & \\text{if } p = 32 \\end{cases}",
      "raw": "\\text{Usable hosts} = \\begin{cases} 2^{32-p} - 2, & \\text{if } p \\le 30 \\\\ 2, & \\text{if } p = 31 \\text{ (RFC 3021 point-to-point)} \\\\ 1, & \\text{if } p = 32 \\end{cases}"
    },
    {
      "title": "Formula (extracted LaTeX)",
      "latex": "\\text{Wildcard mask} = \\neg \\text{Subnet mask} \\quad\\ \\ \\ \\ \\text{Network} = \\text{IP} \\ \\&\\ \\text{Mask} \\quad\\ \\ \\ \\ \\text{Broadcast} = \\text{Network} \\ |\\ \\neg \\text{Mask}",
      "raw": "\\text{Wildcard mask} = \\neg \\text{Subnet mask} \\quad\\ \\ \\ \\ \\text{Network} = \\text{IP} \\ \\&\\ \\text{Mask} \\quad\\ \\ \\ \\ \\text{Broadcast} = \\text{Network} \\ |\\ \\neg \\text{Mask}"
    },
    {
      "title": "Formula (extracted text)",
      "latex": "",
      "raw": "Let \\( p \\) be the prefix length (0–32). Then: \\[ \\text{Total addresses} = 2^{32-p} \\] \\[ \\text{Usable hosts} = \\begin{cases} 2^{32-p} - 2, & \\text{if } p \\le 30 \\\\ 2, & \\text{if } p = 31 \\text{ (RFC 3021 point-to-point)} \\\\ 1, & \\text{if } p = 32 \\end{cases} \\] \\[ \\text{Wildcard mask} = \\neg \\text{Subnet mask} \\quad\\ \\ \\ \\ \\text{Network} = \\text{IP} \\ \\&\\ \\text{Mask} \\quad\\ \\ \\ \\ \\text{Broadcast} = \\text{Network} \\ |\\ \\neg \\text{Mask} \\]"
    }
  ],
  "variables": [],
  "sources": [
    {
      "label": "Home",
      "publisher": "calcdomain.com",
      "url": "https://calcdomain.com/",
      "accessedISO": "2026-01-19"
    },
    {
      "label": "Lifestyle & Everyday",
      "publisher": "calcdomain.com",
      "url": "https://calcdomain.com/lifestyle-everyday",
      "accessedISO": "2026-01-19"
    },
    {
      "label": "Miscellaneous",
      "publisher": "calcdomain.com",
      "url": "https://calcdomain.com/subcategories/miscellaneous",
      "accessedISO": "2026-01-19"
    },
    {
      "label": "RFC 4632 (CIDR)",
      "publisher": "rfc-editor.org",
      "url": "https://www.rfc-editor.org/rfc/rfc4632",
      "accessedISO": "2026-01-19"
    },
    {
      "label": "RFC 791 (IPv4)",
      "publisher": "rfc-editor.org",
      "url": "https://www.rfc-editor.org/rfc/rfc791",
      "accessedISO": "2026-01-19"
    },
    {
      "label": "RFC 950 (Subnetting)",
      "publisher": "rfc-editor.org",
      "url": "https://www.rfc-editor.org/rfc/rfc950",
      "accessedISO": "2026-01-19"
    },
    {
      "label": "RFC 3021 (/31)",
      "publisher": "rfc-editor.org",
      "url": "https://www.rfc-editor.org/rfc/rfc3021",
      "accessedISO": "2026-01-19"
    },
    {
      "label": "IP Address Info",
      "publisher": "calcdomain.com",
      "url": "https://calcdomain.com/ip-calculator",
      "accessedISO": "2026-01-19"
    }
  ],
  "changelog": [
    {
      "dateISO": "2026-01-19",
      "version": "0.1.0-draft",
      "changes": [
        "Initial audit spec draft generated from HTML extraction (review required).",
        "Verify formulas match the calculator engine and convert any text-only formulas to LaTeX.",
        "Confirm sources are authoritative and relevant to the calculator methodology."
      ]
    }
  ]
}
