{
  "slug": "township-to-square-miles",
  "title": "Township to Square Miles Converter – Convert Townships, Acres and km²",
  "canonical": "https://calcdomain.com/township-to-square-miles",
  "version": "0.1.0-draft",
  "lastCodeUpdateISO": "2026-01-19",
  "verifiedByName": "Ugo Candido",
  "verifiedProfileUrl": "https://calcdomain.com/ugocandido",
  "verifiedLinkedInUrl": "https://www.linkedin.com/in/ugocandido92821/",
  "formulas": [
    {
      "title": "Formula (extracted LaTeX)",
      "latex": "','\\",
      "raw": "','\\"
    },
    {
      "title": "Formula (extracted text)",
      "latex": "",
      "raw": "Township area Township area = 6 miles × 6 miles = 36 square miles"
    },
    {
      "title": "Formula (extracted text)",
      "latex": "",
      "raw": "Formula square miles = townships × 36"
    },
    {
      "title": "Formula (extracted text)",
      "latex": "",
      "raw": "Formula townships = square miles ÷ 36"
    },
    {
      "title": "Formula (extracted text)",
      "latex": "",
      "raw": "Formulas acres = square miles × 640 square kilometres = square miles × 2.589988 Combining these: acres = townships × 36 × 640 = townships × 23,040 square kilometres ≈ townships × 36 × 2.589988"
    }
  ],
  "variables": [],
  "sources": [],
  "changelog": [
    {
      "dateISO": "2026-01-19",
      "version": "0.1.0-draft",
      "changes": [
        "Initial audit spec draft generated from HTML extraction (review required).",
        "Verify formulas match the calculator engine and convert any text-only formulas to LaTeX.",
        "Confirm sources are authoritative and relevant to the calculator methodology."
      ]
    }
  ]
}
