{
  "slug": "traffic-signal-timing",
  "title": "Traffic Signal Timing Calculator (Webster's Method)",
  "canonical": "https://calcdomain.com/traffic-signal-timing",
  "version": "0.1.0-draft",
  "lastCodeUpdateISO": "2026-01-19",
  "verifiedByName": "Ugo Candido",
  "verifiedProfileUrl": "https://calcdomain.com/ugocandido",
  "verifiedLinkedInUrl": "https://www.linkedin.com/in/ugocandido92821/",
  "formulas": [
    {
      "title": "Formula (extracted LaTeX)",
      "latex": "','",
      "raw": "','"
    },
    {
      "title": "Formula (extracted text)",
      "latex": "",
      "raw": "The formula to calculate optimal cycle time and green time is: Cycle Time: \\( C = \\frac{1.5L + 5}{1 - \\frac{\\sum Y}{S}} \\) Green Time: \\( G = C \\times \\frac{Y}{\\sum Y} \\)"
    }
  ],
  "variables": [
    {
      "symbol": "T",
      "meaning": "property tax (annual or monthly depending on input)",
      "units": "currency"
    }
  ],
  "sources": [
    {
      "label": "Webster's Method",
      "publisher": "sddc.army.mil",
      "url": "https://www.sddc.army.mil/sites/TEA/Functions/SpecialAssistant/TrafficEngineeringBranch/BMTE/calcTrafficSignals/Pages/calcVehicleIntervals.aspx",
      "accessedISO": "2026-01-19"
    }
  ],
  "changelog": [
    {
      "dateISO": "2026-01-19",
      "version": "0.1.0-draft",
      "changes": [
        "Initial audit spec draft generated from HTML extraction (review required).",
        "Verify formulas match the calculator engine and convert any text-only formulas to LaTeX.",
        "Confirm sources are authoritative and relevant to the calculator methodology."
      ]
    }
  ]
}
